setup.py
RPICappReport/RPICappReport.py
RPICappReport/__init__.py
RPICappReport.egg-info/PKG-INFO
RPICappReport.egg-info/SOURCES.txt
RPICappReport.egg-info/dependency_links.txt
RPICappReport.egg-info/top_level.txt
RPICappReport.egg-info/zip-safe