Metadata-Version: 1.1
Name: RPICappReport
Version: 0.1.3
Summary: some RPI Capp Report parsing functionality
Home-page: http://pythonhosted.org/RPICappReport
Author: linksapprentice1
Author-email: linksapprentice1@gmail.com
License: MIT
Keywords: RPI Capp Report RPICappReport
Platform: UNKNOWN
Classifier: Topic :: Utilities
